QLev/__init__.py
QLev/levDistance.py
QLev-1.9.1.dist-info/LICENSE
QLev-1.9.1.dist-info/METADATA
QLev-1.9.1.dist-info/WHEEL
QLev-1.9.1.dist-info/top_level.txt
QLev-1.9.1.dist-info/RECORD
