Metadata-Version: 2.1
Name: QLev
Version: 1.9.1
Summary: String distance metrics based on Levenshtein and Qwerty Matrix Distance
Home-page: https://github.com/alyssonamaral/QLev
Author: Alysson Amaral
Author-email: alysson.amaral@outlook.com
Keywords: python,levenshtein,qwerty,vector
Classifier: Development Status :: 3 - Alpha
Classifier: Intended Audience :: Science/Research
Classifier: Programming Language :: Python :: 3.9
Classifier: Programming Language :: Python :: 3.10
Classifier: Programming Language :: Python :: 3.11
Classifier: Operating System :: MacOS :: MacOS X
Classifier: Operating System :: Microsoft :: Windows
Classifier: Operating System :: Unix
Classifier: License :: OSI Approved :: MIT License
License-File: LICENSE
Requires-Dist: numpy
